Metadata-Version: 1.0
Name: standard-distributions
Version: 0.0.1
Summary: Probability distributions package
Home-page: UNKNOWN
Author: Kelvin Wahome
Author-email: kevowahome@gmail.com
License: MIT
Platform: UNKNOWN
